easy_amqp/ConnectionManager.py
easy_amqp/Declarator.py
easy_amqp/EasyAMQP.py
easy_amqp/TopologyManager.py
easy_amqp/__init__.py
easy_amqp/consuming.py
easy_amqp/logger.py
easy_amqp/models.py
easy_amqp/parser.py
easy_amqp-1.0.1.dist-info/METADATA
easy_amqp-1.0.1.dist-info/WHEEL
easy_amqp-1.0.1.dist-info/licenses/LICENSE
easy_amqp-1.0.1.dist-info/RECORD
