Metadata-Version: 2.4
Name: easy_amqp
Version: 1.0.1
Summary: easy use of rabbitmq
Project-URL: Homepage, https://github.com/marcr240/easy-amqp
Project-URL: Repository, https://github.com/marcr240/easy-amqp
Author: Marc Rueting
License: MIT
License-File: LICENSE
Keywords: amqp,async,message-queue,pika,rabbitmq
Classifier: Intended Audience :: Developers
Classifier: License :: OSI Approved :: MIT License
Classifier: Operating System :: OS Independent
Classifier: Programming Language :: Python :: 3
Classifier: Programming Language :: Python :: 3.11
Classifier: Programming Language :: Python :: 3.12
Classifier: Topic :: Communications
Classifier: Topic :: Software Development :: Libraries :: Python Modules
Requires-Python: >=3.11
Requires-Dist: pika>=1.3.2
